pryc_test_python_package/__init__.py
pryc_test_python_package/test_module.py
pryc_test_python_package/test_module_common.py
pyrc_test_python_package/__init__.py
pyrc_test_python_package/test_module.py
pyrc_test_python_package/test_module_common.py
test_python_package/__init__.py
test_python_package/test_module.py
test_python_package/test_module_common.py
pyrc_test_python_package-0.0.6.dist-info/METADATA
pyrc_test_python_package-0.0.6.dist-info/WHEEL
pyrc_test_python_package-0.0.6.dist-info/top_level.txt
pyrc_test_python_package-0.0.6.dist-info/RECORD
