Metadata-Version: 2.1
Name: pyrc-test-python-package
Version: 0.0.6
Summary: Test python package to better understand packaging
Home-page: 
Author: Paul Vienneau
Author-email: 
